[{"id": "", "description": "make ana zapiski", "is_completed": false, "priority": "None", "due_date": ["college"], "projects": [], "tags": [], "source": "todo_txt"}, {"id": "", "description": "make fp zapiski", "is_completed": false, "priority": "None", "due_date": ["college"], "projects": [], "tags": [], "source": "todo_txt"}, {"id": "", "description": "ana final", "is_completed": false, "priority": "None", "due_date": ["college"], "projects": [], "tags": ["2024-09-02"], "source": "todo_txt"}, {"id": "", "description": "fp final", "is_completed": false, "priority": "None", "due_date": ["college"], "projects": [], "tags": ["2024-08-26"], "source": "todo_txt"}, {"id": "", "description": "ieps final", "is_completed": false, "priority": "None", "due_date": ["college"], "projects": [], "tags": ["2024-09-03"], "source": "todo_txt"}, {"id": "", "description": "smrpo final", "is_completed": false, "priority": "None", "due_date": ["college"], "projects": [], "tags": ["2024-09-04"], "source": "todo_txt"}, {"id": "", "description": "make ana zapiski", "is_completed": true, "priority": "None", "due_date": ["college"], "projects": [], "tags": [], "source": "todo_txt"}, {"id": "", "description": "ana final   due:", "is_completed": true, "priority": "None", "due_date": ["college"], "projects": ["lj"], "tags": [], "source": "todo_txt"}, {"id": "", "description": "make fp zapiski", "is_completed": true, "priority": "None", "due_date": ["college"], "projects": [], "tags": [], "source": "todo_txt"}, {"id": "", "description": "fp final   due:", "is_completed": true, "priority": "None", "due_date": ["college"], "projects": ["lj"], "tags": [], "source": "todo_txt"}, {"id": "", "description": "ieps final   due:", "is_completed": true, "priority": "None", "due_date": ["college"], "projects": ["lj"], "tags": [], "source": "todo_txt"}, {"id": "", "description": "smrpo final   due:", "is_completed": true, "priority": "None", "due_date": ["college"], "projects": ["lj"], "tags": [], "source": "todo_txt"}, {"id": "7ad74945-29cc-44ea-9895-6869ac644184", "description": "make ana zapiski", "is_completed": false, "priority": "L", "due_date": "", "projects": ["college"], "tags": [], "source": "taskwarrior"}, {"id": "5467b8f9-70be-418d-a6bd-db0a1d52ee23", "description": "make fp zapiski", "is_completed": false, "priority": "L", "due_date": "", "projects": ["college"], "tags": [], "source": "taskwarrior"}, {"id": "7a4ae485-93ed-4f6f-9164-aa71370aa749", "description": "fp final", "is_completed": false, "priority": "M", "due_date": "20240825T220000Z", "projects": ["college"], "tags": ["lj"], "source": "taskwarrior"}, {"id": "1673dbf7-8669-4dda-bd7d-65e648891dd6", "description": "ana final", "is_completed": false, "priority": "M", "due_date": "20240901T220000Z", "projects": ["college"], "tags": ["lj"], "source": "taskwarrior"}, {"id": "94228e83-1381-460e-b9b7-71d7cec09653", "description": "ieps final", "is_completed": false, "priority": "M", "due_date": "20240902T220000Z", "projects": ["college"], "tags": ["lj"], "source": "taskwarrior"}, {"id": "621c503a-44d7-407c-8bfc-b650bfc6e05d", "description": "smrpo final", "is_completed": false, "priority": "M", "due_date": "20240903T220000Z", "projects": ["college"], "tags": ["lj"], "source": "taskwarrior"}, {"id": "33059166-f76e-478b-a346-7ba30c7ab4a2", "description": "ana final   due:", "is_completed": true, "priority": "L", "due_date": "", "projects": ["college"], "tags": ["lj"], "source": "taskwarrior"}, {"id": "2cebdbf2-bee2-4723-be31-6679c267ad6d", "description": "fp final   due:", "is_completed": true, "priority": "L", "due_date": "", "projects": ["college"], "tags": ["lj"], "source": "taskwarrior"}, {"id": "7cc5bdb2-8b43-4083-a161-a44490a27f75", "description": "ieps final   due:", "is_completed": true, "priority": "L", "due_date": "", "projects": ["college"], "tags": ["lj"], "source": "taskwarrior"}, {"id": "8f216d1e-a0a6-4ed0-bfd5-53164e1436be", "description": "smrpo final   due:", "is_completed": true, "priority": "L", "due_date": "", "projects": ["college"], "tags": ["lj"], "source": "taskwarrior"}, {"id": "8255500354", "description": "make ana zapiski", "is_completed": false, "priority": 4, "due_date": "", "projects": ["2337016137"], "tags": [], "source": "todoist"}, {"id": "8255500369", "description": "make fp zapiski", "is_completed": false, "priority": 4, "due_date": "", "projects": ["2337016137"], "tags": [], "source": "todoist"}, {"id": "8255501013", "description": "fp final", "is_completed": false, "priority": 3, "due_date": "2024-08-27", "projects": ["2337016137"], "tags": ["lj"], "source": "todoist"}, {"id": "8255502129", "description": "ana final", "is_completed": false, "priority": 3, "due_date": "2024-09-03", "projects": ["2337016137"], "tags": ["lj"], "source": "todoist"}, {"id": "8255503478", "description": "ieps final", "is_completed": false, "priority": 3, "due_date": "2024-09-04", "projects": ["2337016137"], "tags": ["lj"], "source": "todoist"}, {"id": "8255504144", "description": "smrpo final", "is_completed": false, "priority": 3, "due_date": "2024-09-05", "projects": ["2337016137"], "tags": ["lj"], "source": "todoist"}]